{"info":{"_postman_id":"a9250c4a-fb55-4d91-8d65-9df4d8c1f0b9","name":"folders","schema":"https://schema.getpostman.com/json/collection/v2.1.0/collection.json"},"item":[{"name":"Animals","item":[{"name":"Birds","item":[{"name":"Cardinal","request":{"method":"GET","header":[],"url":{"raw":""}},"response":[]},{"name":"Robin","request":{"method":"GET","header":[],"url":{"raw":""}},"response":[]}]},{"name":"Mammals","item":[{"name":"Bats","request":{"method":"GET","header":[],"url":{"raw":""}},"response":[]},{"name":"Manatees","request":{"method":"GET","header":[],"url":{"raw":""}},"response":[]},{"name":"Zebras","request":{"method":"GET","header":[],"url":{"raw":""}},"response":[]}]}]},{"name":"auth","request":{"method":"GET","header":[],"url":{"raw":""}},"response":[]},{"name":"Auth","request":{"method":"GET","header":[],"url":{"raw":""}},"response":[]},{"name":"Auth - auth","request":{"method":"GET","header":[],"url":{"raw":""}},"response":[]},{"name":"bikes","request":{"method":"GET","header":[],"url":{"raw":""}},"response":[]},{"name":"Bikes","request":{"method":"GET","header":[],"url":{"raw":""}},"response":[]},{"name":"Fruit","item":[{"name":"Apples","request":{"method":"GET","header":[],"url":{"raw":"example.com","host":["example","com"]}},"response":[]},{"name":"Bananas","request":{"method":"GET","header":[],"url":{"raw":"example.com","host":["example","com"]}},"response":[]},{"name":"Mangos","request":{"method":"GET","header":[],"url":{"raw":"example.com","host":["example","com"]}},"response":[]}]},{"name":"users","request":{"method":"GET","header":[],"url":{"raw":""}},"response":[]}]}